scikit_sparse_dev-0.5.0.dev1.dist-info/licenses/LICENSE.txt
sksparse/__init__.py
sksparse/amd.cpython-313-darwin.so
sksparse/amd.pxd
sksparse/btf.cpython-313-darwin.so
sksparse/btf.pxd
sksparse/camd.cpython-313-darwin.so
sksparse/camd.pxd
sksparse/ccolamd.cpython-313-darwin.so
sksparse/ccolamd.pxd
sksparse/cholmod.cpython-313-darwin.so
sksparse/cholmod.pxd
sksparse/colamd.cpython-313-darwin.so
sksparse/colamd.pxd
sksparse/utils.py
scikit_sparse_dev-0.5.0.dev1.dist-info/METADATA
scikit_sparse_dev-0.5.0.dev1.dist-info/WHEEL
scikit_sparse_dev-0.5.0.dev1.dist-info/top_level.txt
scikit_sparse_dev-0.5.0.dev1.dist-info/RECORD
