Metadata-Version: 2.4
Name: scikit-sparse-dev
Version: 0.5.0.dev1
Summary: Scikit-sparse is a Python wrapper for the SuiteSparse sparse matrix library.
Author-email: David Cournapeau <cournape@gmail.com>, Nathaniel Smith <njs@pobox.com>, Dag Sverre Seljebotn <dagss@student.matnat.uio.no>, Leon Barrett <lbarrett@climate.com>, Yuri <yuri@tsoft.com>, Antony Lee <anntzer.lee@gmail.com>, Alex Grigorievskiy <alex.grigorievskiy@gmail.com>, Joscha Reimer <jor@informatik.uni-kiel.de>, Justin Ellis <justin.ellis18@gmail.com>, Aaron Johnson <aaron9035@gmail.com>, Bernard Roesler <bernard.roesler@gmail.com>
Maintainer-email: Bernard Roesler <bernard.roesler@gmail.com>
License-Expression: BSD-2-Clause
Project-URL: Homepage, https://github.com/broesler/scikit-sparse
Project-URL: Bug Tracker, https://github.com/broesler/scikit-sparse/issues
Keywords: sparse,matrix,linear algebra,scipy,numpy
Classifier: Development Status :: 3 - Alpha
Classifier: Environment :: Console
Classifier: Intended Audience :: Developers
Classifier: Intended Audience :: Science/Research
Classifier: Topic :: Scientific/Engineering
Classifier: Topic :: Scientific/Engineering :: Mathematics
Classifier: Programming Language :: Cython
Classifier: Programming Language :: Python :: 3
Classifier: Programming Language :: Python :: 3.10
Classifier: Programming Language :: Python :: 3.11
Classifier: Programming Language :: Python :: 3.12
Requires-Python: >=3.10
License-File: LICENSE.txt
Requires-Dist: numpy>2.0
Requires-Dist: scipy>=1.14
Provides-Extra: dev
Requires-Dist: build; extra == "dev"
Requires-Dist: pre-commit; extra == "dev"
Requires-Dist: pytest; extra == "dev"
Requires-Dist: ruff; extra == "dev"
Requires-Dist: sphinx; extra == "dev"
Requires-Dist: furo; extra == "dev"
Requires-Dist: sphinx-copybutton; extra == "dev"
Dynamic: license-file
